Nanylex/Async.py
Nanylex/Bale.py
Nanylex/Class.py
Nanylex/__init__.py
Nanylex/message.py
Nanylex/version.py
NanyBale-2.2.2.dist-info/LICENCE
NanyBale-2.2.2.dist-info/METADATA
NanyBale-2.2.2.dist-info/WHEEL
NanyBale-2.2.2.dist-info/top_level.txt
NanyBale-2.2.2.dist-info/RECORD
