Metadata-Version: 2.1
Name: NanyBale
Version: 2.2.2
Summary: Library Bale Robot
Author: Nanymous
Author-email: Manymous@gmail.com
License: MIT
Keywords: Nany,NanyBale,NanyBale,nany,bot,Bot,BOT,Robot,ROBOT,robot,self,api,API,Api,Bale,Bale,Bale,Python,python,aiohttp,asyncio
Classifier: Development Status :: 3 - Alpha
Classifier: Intended Audience :: Developers
Classifier: Topic :: Software Development :: Build Tools
Classifier: License :: OSI Approved :: MIT License
Classifier: Programming Language :: Python :: Implementation :: PyPy
Classifier: Programming Language :: Python :: 3
Classifier: Programming Language :: Python :: 3.4
Classifier: Programming Language :: Python :: 3.5
Classifier: Programming Language :: Python :: 3.6
Classifier: Programming Language :: Python :: 3.7
Classifier: Programming Language :: Python :: 3.8
Classifier: Programming Language :: Python :: 3.9
Classifier: Programming Language :: Python :: 3.10
Classifier: Programming Language :: Python :: 3.11
License-File: LICENCE
Requires-Dist: pycryptodome ==3.16.0
Requires-Dist: aiohttp ==3.8.3
Requires-Dist: asyncio ==3.4.3
Requires-Dist: requests ==2.31.0
Requires-Dist: NanyRubika
Requires-Dist: NanyEitaa
Requires-Dist: Nanylibrary
Requires-Dist: Nanybot
Requires-Dist: NanyBale
